odoo10_addon_account_invoice_supplier_ref_unique-10.0.1.0.0-py2.7-nspkg.pth
odoo10_addon_account_invoice_supplier_ref_unique-10.0.1.0.0.dist-info/top_level.txt
odoo10_addon_account_invoice_supplier_ref_unique-10.0.1.0.0.dist-info/WHEEL
odoo10_addon_account_invoice_supplier_ref_unique-10.0.1.0.0.dist-info/RECORD
odoo10_addon_account_invoice_supplier_ref_unique-10.0.1.0.0.dist-info/metadata.json
odoo10_addon_account_invoice_supplier_ref_unique-10.0.1.0.0.dist-info/DESCRIPTION.rst
odoo10_addon_account_invoice_supplier_ref_unique-10.0.1.0.0.dist-info/METADATA
odoo10_addon_account_invoice_supplier_ref_unique-10.0.1.0.0.dist-info/namespace_packages.txt
odoo/addons/account_invoice_supplier_ref_unique/__manifest__.py
odoo/addons/account_invoice_supplier_ref_unique/__init__.py
odoo/addons/account_invoice_supplier_ref_unique/README.rst
odoo/addons/account_invoice_supplier_ref_unique/models/account_invoice.py
odoo/addons/account_invoice_supplier_ref_unique/models/__init__.py
odoo/addons/account_invoice_supplier_ref_unique/i18n/sl.po
odoo/addons/account_invoice_supplier_ref_unique/i18n/fr.po
odoo/addons/account_invoice_supplier_ref_unique/i18n/account_invoice_supplier_ref_unique.pot
odoo/addons/account_invoice_supplier_ref_unique/views/account_invoice.xml
odoo/addons/account_invoice_supplier_ref_unique/tests/__init__.py
odoo/addons/account_invoice_supplier_ref_unique/tests/test_account_invoice_supplier_ref_unique.py
