Metadata-Version: 2.0
Name: odoo10-addon-account-invoice-supplier-ref-unique
Version: 10.0.1.0.0
Summary: Checks that supplier invoices are not entered twice
Home-page: http://www.savoirfairelinux.com
Author: UNKNOWN
Author-email: UNKNOWN
License: AGPL-3
Platform: UNKNOWN
Requires-Dist: odoo (<10.1dev,>=10.0)
Classifier: Programming Language :: Python :: 2.7
Classifier: Framework :: Odoo
Classifier: License :: OSI Approved :: GNU Affero General Public License v3
